setup.cfg
setup.py
src/BCSFE_KCC/__init__.py
src/BCSFE_KCC/__main__.py
src/BCSFE_KCC/adb_handler.py
src/BCSFE_KCC/config_manager.py
src/BCSFE_KCC/csv_handler.py
src/BCSFE_KCC/feature_handler.py
src/BCSFE_KCC/game_data_getter.py
src/BCSFE_KCC/helper.py
src/BCSFE_KCC/item.py
src/BCSFE_KCC/locale_handler.py
src/BCSFE_KCC/managed_item.py
src/BCSFE_KCC/parse_save.py
src/BCSFE_KCC/patcher.py
src/BCSFE_KCC/root_handler.py
src/BCSFE_KCC/serialise_save.py
src/BCSFE_KCC/server_handler.py
src/BCSFE_KCC/tracker.py
src/BCSFE_KCC/updater.py
src/BCSFE_KCC/user_input_handler.py
src/BCSFE_KCC/edits/__init__.py
src/BCSFE_KCC/edits/basic/__init__.py
src/BCSFE_KCC/edits/basic/basic_items.py
src/BCSFE_KCC/edits/basic/catfruit.py
src/BCSFE_KCC/edits/basic/catseyes.py
src/BCSFE_KCC/edits/basic/ototo_base_mats.py
src/BCSFE_KCC/edits/basic/talent_orbs.py
src/BCSFE_KCC/edits/basic/talent_orbs_new.py
src/BCSFE_KCC/edits/cats/__init__.py
src/BCSFE_KCC/edits/cats/cat_helper.py
src/BCSFE_KCC/edits/cats/cat_id_selector.py
src/BCSFE_KCC/edits/cats/chara_drop.py
src/BCSFE_KCC/edits/cats/clear_cat_guide.py
src/BCSFE_KCC/edits/cats/evolve_cats.py
src/BCSFE_KCC/edits/cats/get_remove_cats.py
src/BCSFE_KCC/edits/cats/talents.py
src/BCSFE_KCC/edits/cats/upgrade_blue.py
src/BCSFE_KCC/edits/cats/upgrade_cats.py
src/BCSFE_KCC/edits/gamototo/__init__.py
src/BCSFE_KCC/edits/gamototo/fix_gamatoto.py
src/BCSFE_KCC/edits/gamototo/gamatoto_xp.py
src/BCSFE_KCC/edits/gamototo/helpers.py
src/BCSFE_KCC/edits/gamototo/ototo_cat_cannon.py
src/BCSFE_KCC/edits/levels/__init__.py
src/BCSFE_KCC/edits/levels/aku.py
src/BCSFE_KCC/edits/levels/allow_filibuster_clearing.py
src/BCSFE_KCC/edits/levels/behemoth_culling.py
src/BCSFE_KCC/edits/levels/clear_tutorial.py
src/BCSFE_KCC/edits/levels/enigma_stages.py
src/BCSFE_KCC/edits/levels/event_stages.py
src/BCSFE_KCC/edits/levels/gauntlet.py
src/BCSFE_KCC/edits/levels/itf_timed_scores.py
src/BCSFE_KCC/edits/levels/legend_quest.py
src/BCSFE_KCC/edits/levels/main_story.py
src/bcsfe_kcc.egg-info/PKG-INFO
src/bcsfe_kcc.egg-info/SOURCES.txt
src/bcsfe_kcc.egg-info/dependency_links.txt
src/bcsfe_kcc.egg-info/requires.txt
src/bcsfe_kcc.egg-info/top_level.txt