Metadata-Version: 2.1
Name: bcsfe-kcc
Version: 2.7.62
Summary: BCSFE_Python personal api
Home-page: UNKNOWN
Author: CintagramABP
License: UNKNOWN
Platform: UNKNOWN
Requires-Python: >=3.9
Provides-Extra: testing
